nlaftn/__init__.py
nlaftn-0.4.0.dist-info/DESCRIPTION.rst
nlaftn-0.4.0.dist-info/METADATA
nlaftn-0.4.0.dist-info/RECORD
nlaftn-0.4.0.dist-info/WHEEL
nlaftn-0.4.0.dist-info/metadata.json
nlaftn-0.4.0.dist-info/top_level.txt
